extended_settings/__init__.py
extended_settings/admin.py
extended_settings/apps.py
extended_settings/models.py
extended_settings/tests.py
extended_settings/migrations/0001_initial.py
extended_settings/migrations/__init__.py
django_extended_settings-1.3.2.dist-info/LICENSE.txt
django_extended_settings-1.3.2.dist-info/METADATA
django_extended_settings-1.3.2.dist-info/WHEEL
django_extended_settings-1.3.2.dist-info/top_level.txt
django_extended_settings-1.3.2.dist-info/RECORD
